c_secp256k1-0.0.6.data/purelib/c_secp256k1/__init__.py
c_secp256k1-0.0.6.data/purelib/c_secp256k1/_c_secp256k1.py
c_secp256k1-0.0.6.data/purelib/c_secp256k1/libsecp256k1.0.dylib
c_secp256k1-0.0.6.dist-info/DESCRIPTION.rst
c_secp256k1-0.0.6.dist-info/METADATA
c_secp256k1-0.0.6.dist-info/metadata.json
c_secp256k1-0.0.6.dist-info/RECORD
c_secp256k1-0.0.6.dist-info/top_level.txt
c_secp256k1-0.0.6.dist-info/WHEEL
