Metadata-Version: 2.0
Name: c-secp256k1
Version: 0.0.6
Summary: secp256k1 wrapped with cffi to use with python
Home-page: https://github.com/czepluch/pysecp256k1
Author: Jacob Stenum Czepluch
Author-email: j.czepluch@gmail.com
License: MIT
Platform: UNKNOWN
Classifier: Programming Language :: Python :: 2
Classifier: Programming Language :: Python :: 2.7
Classifier: Programming Language :: Python :: Implementation :: PyPy
Requires-Dist: cffi (>=1.2.1)
Requires-Dist: bitcoin (>=1.1.36)
